a2/__init__.py
a2/aich.py
aich-0.0.5.dist-info/LICENSE
aich-0.0.5.dist-info/METADATA
aich-0.0.5.dist-info/WHEEL
aich-0.0.5.dist-info/top_level.txt
aich-0.0.5.dist-info/RECORD
