Metadata-Version: 2.1
Name: aich
Version: 0.0.5
Summary: Encrypt Words From Any Language. Get Token In Hindi.
Home-page: https://github.com/arijitaich/AICH-Encryption
Author: Arijit Aich
Author-email: a2.arijitaich@gmail.com
License: UNKNOWN
Platform: UNKNOWN
Classifier: Programming Language :: Python :: 3
Classifier: License :: OSI Approved :: MIT License
Classifier: Operating System :: OS Independent
